CassandraCQLLibrary.py
robotframework_cassandracqllibrary-2.0.1.dist-info/LICENSE
robotframework_cassandracqllibrary-2.0.1.dist-info/METADATA
robotframework_cassandracqllibrary-2.0.1.dist-info/WHEEL
robotframework_cassandracqllibrary-2.0.1.dist-info/top_level.txt
robotframework_cassandracqllibrary-2.0.1.dist-info/RECORD
