Metadata-Version: 2.1
Name: robotframework-cassandracqllibrary
Version: 2.0.1
Summary: A Robot Framework Cassandra Database Library
Home-page: https://github.com/peterservice-rnd/robotframework-cassandracqllibrary
Author: JSC PETER-SERVICE
Author-email: drse_aist_all@billing.ru
License: Apache License 2.0
Keywords: testing testautomation robotframework cassandra cql
Platform: UNKNOWN
Classifier: Development Status :: 5 - Production/Stable
Classifier: Intended Audience :: Developers
Classifier: Topic :: Software Development :: Testing
Classifier: License :: OSI Approved :: Apache Software License
Classifier: Programming Language :: Python :: 3.5
Classifier: Programming Language :: Python :: 3.6
Classifier: Framework :: Robot Framework :: Library
Requires-Dist: cassandra-driver (==3.12.0)
Requires-Dist: robotframework (==3.0.2)
